_pylibczi.cp36-win_amd64.pyd
pylibczi/CziFile.py
pylibczi/CziScene.py
pylibczi/__init__.py
pylibczi/_version.py
pylibczi-1.1.1.data/data/libCZI.dll
pylibczi-1.1.1.dist-info/METADATA
pylibczi-1.1.1.dist-info/RECORD
pylibczi-1.1.1.dist-info/WHEEL
pylibczi-1.1.1.dist-info/top_level.txt
