Metadata-Version: 2.1
Name: pylibczi
Version: 1.1.1
Summary: Python module utilizing libCZI for reading Zeiss CZI files.
Home-page: https://github.com/elhuhdron/pylibczi
Author: Paul Watkins
Author-email: pwatkins@gmail.com
License: UNKNOWN
Platform: UNKNOWN
Requires-Dist: scipy
Requires-Dist: numpy
Requires-Dist: lxml
